iran_encoding/__init__.py
iran_encoding/c_wrapper.py
iran_encoding/cli.py
iran_encoding/core.py
iran_encoding-1.1.0.dist-info/licenses/LICENSE
iran_encoding-1.1.0.dist-info/METADATA
iran_encoding-1.1.0.dist-info/WHEEL
iran_encoding-1.1.0.dist-info/entry_points.txt
iran_encoding-1.1.0.dist-info/top_level.txt
iran_encoding-1.1.0.dist-info/RECORD
